LICENSE
README.md
setup.py
nlecloud_framework/__init__.py
nlecloud_framework/run.py
nlecloud_framework.egg-info/PKG-INFO
nlecloud_framework.egg-info/SOURCES.txt
nlecloud_framework.egg-info/dependency_links.txt
nlecloud_framework.egg-info/requires.txt
nlecloud_framework.egg-info/top_level.txt
nlecloud_framework/libs/__init__.py
nlecloud_framework/libs/chatgpt/__init__.py
nlecloud_framework/libs/chatgpt/open_chat_gpt.py
nlecloud_framework/libs/exam/__init__.py
nlecloud_framework/libs/exam/exam_paper.py
nlecloud_framework/utils/__init__.py
nlecloud_framework/utils/crypto.py
nlecloud_framework/utils/nlecommon.py
nlecloud_framework/utils/oss.py
nlecloud_framework/utils/prt_cmd_color.py
nlecloud_framework/utils/range.py
nlecloud_framework/utils/time.py
nlecloud_framework/utils/uuid.py
nlecloud_framework/utils/yaml.py